yms_zsl/__init__.py
yms_zsl/version.py
yms_zsl/models/CAE.py
yms_zsl/models/HSAZLM.py
yms_zsl/models/VAE.py
yms_zsl/models/__init__.py
yms_zsl/models/my_models.py
yms_zsl/tools/__init__.py
yms_zsl/tools/dataset.py
yms_zsl/tools/plotting.py
yms_zsl/tools/tool.py
yms_zsl/tools/train_eval_utils.py
yms_zsl/tools/wandb_tool.py
yms_zsl/train/__init__.py
yms_zsl/train/main.py
yms_zsl/train/predict.py
yms_zsl/train/semantics.py
yms_zsl/train/train.py
yms_zsl/train/train_decae.py
yms_zsl/train/train_fcnn.py
yms_zsl/train/train_feature_extractor.py
yms_zsl-0.1.5.dist-info/licenses/LICENSE
yms_zsl-0.1.5.dist-info/METADATA
yms_zsl-0.1.5.dist-info/WHEEL
yms_zsl-0.1.5.dist-info/top_level.txt
yms_zsl-0.1.5.dist-info/RECORD
